kafkademia/__init__.py
kafkademia/consumidor.py
kafkademia/ejemplos.py
kafkademia/kafkademia.py
kafkademia/productor.py
kafkademia/utils.py
kafkademia-0.4.dist-info/METADATA
kafkademia-0.4.dist-info/WHEEL
kafkademia-0.4.dist-info/entry_points.txt
kafkademia-0.4.dist-info/top_level.txt
kafkademia-0.4.dist-info/RECORD
