Metadata-Version: 2.1
Name: kafkademia
Version: 0.4
Summary: UNKNOWN
Author-email: ulises.ramirez@datalytics.com
License: MIT
Platform: UNKNOWN
Requires-Dist: kafka-python
